ethernot/__init__.py
ethernot/ethernot.py
ethernot-0.2.0.dist-info/licenses/LICENSE
ethernot-0.2.0.dist-info/WHEEL
ethernot-0.2.0.dist-info/entry_points.txt
ethernot-0.2.0.dist-info/METADATA
ethernot-0.2.0.dist-info/RECORD
