Metadata-Version: 2.4
Name: ethernot
Version: 0.2.0
Summary: Simple, anyonymous chat app where messages are never saved to a disk. Ever.
License-Expression: GPL-3.0-only
License-File: LICENSE
Requires-Dist: prompt-toolkit>=3.0.52
Requires-Python: >=3.12
